CHANGES.txt
LICENSE.txt
MANIFEST.in
README.rst
setup.py
HanoiVis.egg-info/PKG-INFO
HanoiVis.egg-info/SOURCES.txt
HanoiVis.egg-info/dependency_links.txt
HanoiVis.egg-info/top_level.txt
hanoivis/__init__.py
hanoivis/hanoivis.py
hanoivis/test/__init__.py