Metadata-Version: 2.1
Name: HanoiVis
Version: 0.1.3
Summary: Tower of Hanoi visualiser
Home-page: http://pypi.python.org/pypi/HanoiVis/
Author: Arvind Olag
Author-email: arvindolag@gmail.com
License: LICENSE.txt
License-File: LICENSE.txt
